DLtorch/__init__.py
DLtorch/main.py
DLtorch/version.py
DLtorch/adv_attack/FGSM.py
DLtorch/adv_attack/PGD.py
DLtorch/adv_attack/__init__.py
DLtorch/adv_attack/base.py
DLtorch/component/__init__.py
DLtorch/component/criterion.py
DLtorch/component/dataset.py
DLtorch/component/lr_scheduler.py
DLtorch/component/model.py
DLtorch/component/objective.py
DLtorch/component/optimizer.py
DLtorch/component/trainer.py
DLtorch/datasets/Cifar10.py
DLtorch/datasets/Cifar100.py
DLtorch/datasets/FashionMNIST.py
DLtorch/datasets/Imagenet.py
DLtorch/datasets/MNIST.py
DLtorch/datasets/SVHN.py
DLtorch/datasets/__init__.py
DLtorch/datasets/base.py
DLtorch/models/__init__.py
DLtorch/models/MNIST/LeNet.py
DLtorch/models/MNIST/__init__.py
DLtorch/models/cifar/DenseNet.py
DLtorch/models/cifar/LeNet.py
DLtorch/models/cifar/WideResNet.py
DLtorch/models/cifar/__init__.py
DLtorch/models/cifar/resnet.py
DLtorch/objective/__init__.py
DLtorch/objective/base.py
DLtorch/objective/classification_adversarial_objective.py
DLtorch/objective/classification_objective.py
DLtorch/train/CNNFinalTrainer.py
DLtorch/train/__init__.py
DLtorch/train/base.py
DLtorch/utils/__init__.py
DLtorch/utils/common_utils.py
DLtorch/utils/logger.py
DLtorch/utils/python_utils.py
DLtorch/utils/torch_utils.py
DLtorch-1.0.0.dist-info/LICENSE
DLtorch-1.0.0.dist-info/METADATA
DLtorch-1.0.0.dist-info/WHEEL
DLtorch-1.0.0.dist-info/entry_points.txt
DLtorch-1.0.0.dist-info/top_level.txt
DLtorch-1.0.0.dist-info/RECORD
