Metadata-Version: 2.1
Name: DLtorch
Version: 1.0.0
Summary: Deep Learning Framework based on Pytorch
Home-page: https://github.com/zhaojb17/DLtorch
Author: Junbo Zhao
Author-email: zhaojb17@mails.tsinghua.edu.cn
License: MIT
Platform: UNKNOWN
Classifier: Programming Language :: Python :: 3
Classifier: Operating System :: OS Independent
Classifier: License :: OSI Approved :: MIT License
Requires-Dist: torch (<1.5.0,>=1.0.0)
Requires-Dist: torchvision (>=0.4.0)
Requires-Dist: numpy
Requires-Dist: click
Requires-Dist: matplotlib
Requires-Dist: torchviz
